triton/__init__.py
triton/_internal_testing.py
triton/errors.py
triton/testing.py
triton/_C/libGPUHello.so
triton/_C/libproton.so
triton/_C/include/CMakeLists.txt
triton/_C/include/triton/CMakeLists.txt
triton/_C/include/triton/Analysis/Alias.h
triton/_C/include/triton/Analysis/Allocation.h
triton/_C/include/triton/Analysis/AxisInfo.h
triton/_C/include/triton/Analysis/Membar.h
triton/_C/include/triton/Analysis/Utility.h
triton/_C/include/triton/Conversion/CMakeLists.txt
triton/_C/include/triton/Conversion/MLIRTypes.h
triton/_C/include/triton/Conversion/TritonGPUToLLVM/AsmFormat.h
triton/_C/include/triton/Conversion/TritonGPUToLLVM/CMakeLists.txt
triton/_C/include/triton/Conversion/TritonGPUToLLVM/ElementwiseOpToLLVMBase.h
triton/_C/include/triton/Conversion/TritonGPUToLLVM/Passes.h
triton/_C/include/triton/Conversion/TritonGPUToLLVM/Passes.td
triton/_C/include/triton/Conversion/TritonGPUToLLVM/PatternTritonGPUOpToLLVM.h
triton/_C/include/triton/Conversion/TritonGPUToLLVM/Patterns.h
triton/_C/include/triton/Conversion/TritonGPUToLLVM/TargetInfoBase.h
triton/_C/include/triton/Conversion/TritonGPUToLLVM/TypeConverter.h
triton/_C/include/triton/Conversion/TritonGPUToLLVM/Utility.h
triton/_C/include/triton/Conversion/TritonToTritonGPU/CMakeLists.txt
triton/_C/include/triton/Conversion/TritonToTritonGPU/Passes.h
triton/_C/include/triton/Conversion/TritonToTritonGPU/Passes.td
triton/_C/include/triton/Conversion/TritonToTritonGPU/TritonToTritonGPUPass.h
triton/_C/include/triton/Dialect/CMakeLists.txt
triton/_C/include/triton/Dialect/Triton/CMakeLists.txt
triton/_C/include/triton/Dialect/Triton/IR/CMakeLists.txt
triton/_C/include/triton/Dialect/Triton/IR/Dialect.h
triton/_C/include/triton/Dialect/Triton/IR/Interfaces.h
triton/_C/include/triton/Dialect/Triton/IR/Traits.h
triton/_C/include/triton/Dialect/Triton/IR/TritonAttrDefs.td
triton/_C/include/triton/Dialect/Triton/IR/TritonDialect.td
triton_rocm-3.0.0.dist-info/METADATA,sha256=fe9c1cd71dba5ee429713c79587114abd230fc4193c9e14cbc44470c1a92a086
triton_rocm-3.0.0.dist-info/WHEEL
triton_rocm-3.0.0.dist-info/entry_points.txt
triton_rocm-3.0.0.dist-info/top_level.txt
triton_rocm-3.0.0.dist-info/RECORD
